{
   "Alignment" : null,
   "Point" : null,
   "actors" : [
      {
         "Alignment" : [ 0, 0 ],
         "Alpha" : 1.0,
         "Angle" : 0.0,
         "Colour" : 4294967295,
         "Flip" : 0,
         "Position" : [ 0.0, 0.0 ],
         "Scale" : [ 0.0, 0.0 ],
         "Shown" : true,
         "sprite" : "vortex_smoke",
         "type" : 1,
         "uid" : 3
      },
      {
         "Alignment" : [ 0, 0 ],
         "Alpha" : 1.0,
         "Angle" : 0.0,
         "Colour" : 4294967295,
         "Flip" : 0,
         "Position" : [ 0.0, -11.0 ],
         "Scale" : [ 0.0, 0.0 ],
         "Shown" : true,
         "sprite" : "vortex_smoke",
         "type" : 1,
         "uid" : 4
      },
      {
         "Alignment" : [ 0, 0 ],
         "Alpha" : 1.0,
         "Angle" : 0.0,
         "Colour" : 4294967295,
         "Flip" : 0,
         "Position" : [ 0.0, 11.0 ],
         "Scale" : [ 0.0, 0.0 ],
         "Shown" : true,
         "sprite" : "vortex_smoke",
         "type" : 1,
         "uid" : 5
      },
      {
         "Alignment" : [ 0, 0 ],
         "Alpha" : 1.0,
         "Angle" : 0.0,
         "Colour" : 4294967295,
         "Flip" : 0,
         "Position" : [ 0.0, 0.0 ],
         "Scale" : [ 3.349999904632568, 7.349999904632568 ],
         "Shown" : false,
         "sprite" : "vortex_smoke",
         "type" : 1,
         "uid" : 6
      },
      {
         "Alignment" : [ 0, 0 ],
         "Alpha" : 1.0,
         "Angle" : 0.0,
         "Colour" : 4294967295,
         "Flip" : 0,
         "Position" : [ 0.0, -32.0 ],
         "Scale" : [ 0.0, 0.0 ],
         "Shown" : true,
         "sprite" : "vortex_smoke",
         "type" : 1,
         "uid" : 7
      },
      {
         "Alignment" : [ 0, 0 ],
         "Alpha" : 1.0,
         "Angle" : 0.0,
         "Colour" : 4294967295,
         "Flip" : 0,
         "Position" : [ 0.0, 32.0 ],
         "Scale" : [ 0.0, 0.0 ],
         "Shown" : true,
         "sprite" : "vortex_smoke",
         "type" : 1,
         "uid" : 8
      }
   ],
   "customvariables" : null,
   "labels" : null,
   "stageOptions" : {
      "SpriteInfo" : [
         {
            "SpriteInfo" : "vortex_smoke",
            "Texture" : "vortex_sheet"
         }
      ],
      "StageLength" : 0.2039930522441864,
      "Version" : 1
   },
   "timelines" : [
      {
         "spriteuid" : 3,
         "stage" : [
            {
               "Alignment" : [ 0, 0 ],
               "Alpha" : 1.0,
               "Angle" : 0.0,
               "Colour" : 4294967295,
               "Flip" : 0,
               "Position" : [ 0.0, 0.0 ],
               "Scale" : [ 0.0, 0.0 ],
               "Shown" : true,
               "Time" : 0.0
            },
            {
               "Alignment" : [ 0, 0 ],
               "Alpha" : 1.0,
               "Angle" : 0.0,
               "Colour" : 4294967295,
               "Flip" : 0,
               "Position" : [ 0.0, 0.0 ],
               "Scale" : [ 25.0, 1.0 ],
               "Shown" : true,
               "Time" : 0.06857638806104660
            },
            {
               "Alignment" : [ 0, 0 ],
               "Alpha" : 1.0,
               "Angle" : 0.0,
               "Colour" : 4294967295,
               "Flip" : 0,
               "Position" : [ 0.0, 0.0 ],
               "Scale" : [ 4.349999904632568, 1.0 ],
               "Shown" : false,
               "Time" : 0.1527777761220932
            }
         ]
      },
      {
         "spriteuid" : 4,
         "stage" : [
            {
               "Alignment" : [ 0, 0 ],
               "Alpha" : 1.0,
               "Angle" : 0.0,
               "Colour" : 4294967295,
               "Flip" : 0,
               "Position" : [ 0.0, -11.0 ],
               "Scale" : [ 0.0, 0.0 ],
               "Shown" : true,
               "Time" : 0.0
            },
            {
               "Alignment" : [ 0, 0 ],
               "Alpha" : 1.0,
               "Angle" : 0.0,
               "Colour" : 4294967295,
               "Flip" : 0,
               "Position" : [ 0.0, -10.0 ],
               "Scale" : [ 20.0, 1.0 ],
               "Shown" : true,
               "Time" : 0.08420138806104660
            },
            {
               "Alignment" : [ 0, 0 ],
               "Alpha" : 1.0,
               "Angle" : 0.0,
               "Colour" : 4294967295,
               "Flip" : 0,
               "Position" : [ 0.0, -11.0 ],
               "Scale" : [ 3.781744003295898, 1.0 ],
               "Shown" : false,
               "Time" : 0.1527777761220932
            }
         ]
      },
      {
         "spriteuid" : 5,
         "stage" : [
            {
               "Alignment" : [ 0, 0 ],
               "Alpha" : 1.0,
               "Angle" : 0.0,
               "Colour" : 4294967295,
               "Flip" : 0,
               "Position" : [ 0.0, 11.0 ],
               "Scale" : [ 0.0, 0.0 ],
               "Shown" : true,
               "Time" : 0.0
            },
            {
               "Alignment" : [ 0, 0 ],
               "Alpha" : 1.0,
               "Angle" : 0.0,
               "Colour" : 4294967295,
               "Flip" : 0,
               "Position" : [ 0.0, 10.0 ],
               "Scale" : [ 15.91639328002930, 1.0 ],
               "Shown" : true,
               "Time" : 0.08246527612209320
            },
            {
               "Alignment" : [ 0, 0 ],
               "Alpha" : 1.0,
               "Angle" : 0.0,
               "Colour" : 4294967295,
               "Flip" : 0,
               "Position" : [ 0.0, 10.0 ],
               "Scale" : [ 3.900000095367432, 1.0 ],
               "Shown" : false,
               "Time" : 0.1527777761220932
            }
         ]
      },
      {
         "spriteuid" : 6,
         "stage" : [
            {
               "Alignment" : [ 0, 0 ],
               "Alpha" : 1.0,
               "Angle" : 0.0,
               "Colour" : 4294967295,
               "Flip" : 0,
               "Position" : [ 0.0, 0.0 ],
               "Scale" : [ 3.349999904632568, 7.349999904632568 ],
               "Shown" : false,
               "Time" : 0.0
            },
            {
               "Alignment" : [ 0, 0 ],
               "Alpha" : 1.0,
               "Angle" : 0.0,
               "Colour" : 4294967295,
               "Flip" : 0,
               "Position" : [ 0.0, 0.0 ],
               "Scale" : [ 3.349999904632568, 7.349999904632568 ],
               "Shown" : true,
               "Time" : 0.09895833581686020
            },
            {
               "Alignment" : [ 0, 0 ],
               "Alpha" : 0.9647058844566345,
               "Angle" : 0.0,
               "Colour" : 4143972351,
               "Flip" : 0,
               "Position" : [ 0.0, 0.0 ],
               "Scale" : [ 4.0, 14.0 ],
               "Shown" : true,
               "Time" : 0.1527777761220932
            },
            {
               "Alignment" : [ 0, 0 ],
               "Alpha" : 0.0,
               "Angle" : 0.0,
               "Colour" : 16777215,
               "Flip" : 0,
               "Position" : [ 0.0, 0.0 ],
               "Scale" : [ 3.650000095367432, 15.0 ],
               "Shown" : true,
               "Time" : 0.2031250
            }
         ]
      },
      {
         "spriteuid" : 7,
         "stage" : [
            {
               "Alignment" : [ 0, 0 ],
               "Alpha" : 1.0,
               "Angle" : 0.0,
               "Colour" : 4294967295,
               "Flip" : 0,
               "Position" : [ 0.0, -32.0 ],
               "Scale" : [ 0.0, 0.0 ],
               "Shown" : true,
               "Time" : 0.0
            },
            {
               "Alignment" : [ 0, 0 ],
               "Alpha" : 1.0,
               "Angle" : 0.0,
               "Colour" : 4294967295,
               "Flip" : 0,
               "Position" : [ 0.0, -32.0 ],
               "Scale" : [ 14.39999961853027, 0.5500000119209290 ],
               "Shown" : true,
               "Time" : 0.08072916418313980
            },
            {
               "Alignment" : [ 0, 0 ],
               "Alpha" : 1.0,
               "Angle" : 0.0,
               "Colour" : 4294967295,
               "Flip" : 0,
               "Position" : [ 0.0, -32.0 ],
               "Scale" : [ 2.250, 0.1000000014901161 ],
               "Shown" : false,
               "Time" : 0.1527777761220932
            }
         ]
      },
      {
         "spriteuid" : 8,
         "stage" : [
            {
               "Alignment" : [ 0, 0 ],
               "Alpha" : 1.0,
               "Angle" : 0.0,
               "Colour" : 4294967295,
               "Flip" : 0,
               "Position" : [ 0.0, 32.0 ],
               "Scale" : [ 0.0, 0.0 ],
               "Shown" : true,
               "Time" : 0.0
            },
            {
               "Alignment" : [ 0, 0 ],
               "Alpha" : 1.0,
               "Angle" : 0.0,
               "Colour" : 4294967295,
               "Flip" : 0,
               "Position" : [ 0.0, 32.0 ],
               "Scale" : [ 14.39999961853027, 0.5500000119209290 ],
               "Shown" : true,
               "Time" : 0.07725694775581360
            },
            {
               "Alignment" : [ 0, 0 ],
               "Alpha" : 1.0,
               "Angle" : 0.0,
               "Colour" : 4294967295,
               "Flip" : 0,
               "Position" : [ 0.0, 32.0 ],
               "Scale" : [ 3.750, 0.0 ],
               "Shown" : false,
               "Time" : 0.1545138955116272
            }
         ]
      }
   ]
}
